LICENSE
MANIFEST.in
README.rst
setup.py
eep/__init__.py
eep/eep.py
eep.egg-info/PKG-INFO
eep.egg-info/SOURCES.txt
eep.egg-info/dependency_links.txt
eep.egg-info/top_level.txt
tests/__init__.py
tests/test_eep.py