Metadata-Version: 1.0
Name: eep
Version: 0.1.3
Summary: Emacs style, point based string search-replace library for python
Home-page: https://github.com/lepisma/eep
Author: Abhinav Tushar
Author-email: abhinav.tushar.vs@gmail.com
License: MIT
Keywords: eep string search replace
Platform: UNKNOWN
